awslabs/__init__.py
awslabs/nova_canvas_mcp_server/__init__.py
awslabs/nova_canvas_mcp_server/consts.py
awslabs/nova_canvas_mcp_server/models.py
awslabs/nova_canvas_mcp_server/novacanvas.py
awslabs/nova_canvas_mcp_server/server.py
awslabs_nova_canvas_mcp_server-1.0.11.dist-info/METADATA
awslabs_nova_canvas_mcp_server-1.0.11.dist-info/WHEEL
awslabs_nova_canvas_mcp_server-1.0.11.dist-info/entry_points.txt
awslabs_nova_canvas_mcp_server-1.0.11.dist-info/licenses/LICENSE
awslabs_nova_canvas_mcp_server-1.0.11.dist-info/licenses/NOTICE
awslabs_nova_canvas_mcp_server-1.0.11.dist-info/RECORD
