Metadata-Version: 2.4
Name: awslabs.nova-canvas-mcp-server
Version: 1.0.11
Summary: An AWS Labs Model Context Protocol (MCP) server for Amazon Nova Canvas
Project-URL: Homepage, https://awslabs.github.io/mcp/
Project-URL: Documentation, https://awslabs.github.io/mcp/servers/nova-mcp-server/
Project-URL: Source, https://github.com/awslabs/mcp.git
Project-URL: Bug Tracker, https://github.com/awslabs/mcp/issues
Project-URL: Changelog, https://github.com/awslabs/mcp/blob/main/src/nova-mcp-server/CHANGELOG.md
Author: Amazon Web Services
Author-email: AWSLabs MCP <203918161+awslabs-mcp@users.noreply.github.com>
License: Apache-2.0
License-File: LICENSE
License-File: NOTICE
Classifier: License :: OSI Approved :: Apache Software License
Classifier: Operating System :: OS Independent
Classifier: Programming Language :: Python
Classifier: Programming Language :: Python :: 3
Classifier: Programming Language :: Python :: 3.10
Classifier: Programming Language :: Python :: 3.11
Classifier: Programming Language :: Python :: 3.12
Classifier: Programming Language :: Python :: 3.13
Requires-Python: >=3.10
Requires-Dist: boto3>=1.37.24
Requires-Dist: loguru>=0.7.3
Requires-Dist: mcp[cli]>=1.23.0
Requires-Dist: pydantic>=2.11.1
Requires-Dist: pytest-asyncio>=0.26.0
Requires-Dist: pytest-cov>=4.1.0
Requires-Dist: pytest-mock>=3.12.0
Requires-Dist: pytest>=8.0.0
